pielab/__init__.py
pielab/__main__.py
pielab-0.1.0.dist-info/LICENSE
pielab-0.1.0.dist-info/METADATA
pielab-0.1.0.dist-info/WHEEL
pielab-0.1.0.dist-info/RECORD
