Metadata-Version: 2.1
Name: pielab
Version: 0.1.0
Summary: electro lab with python
License: BSDv3
Author: daniel
Author-email: daniel.krpelik@vsb.cz
Requires-Python: >=3.10,<4.0
Classifier: License :: Other/Proprietary License
Classifier: Programming Language :: Python :: 3
Classifier: Programming Language :: Python :: 3.10
Classifier: Programming Language :: Python :: 3.11
Requires-Dist: matplotlib (>=3.7.1,<4.0.0)
Requires-Dist: networkx (>=3.0,<4.0)
Requires-Dist: numpy (>=1.24.2,<2.0.0)
